powerdataclass/VERSION.py
powerdataclass/__init__.py
powerdataclass/powerconfig.py
powerdataclass-1.4.0.dist-info/LICENSE
powerdataclass-1.4.0.dist-info/METADATA
powerdataclass-1.4.0.dist-info/WHEEL
powerdataclass-1.4.0.dist-info/top_level.txt
powerdataclass-1.4.0.dist-info/RECORD
