Metadata-Version: 2.1
Name: powerdataclass
Version: 1.4.0
Summary: Power Dataclass: dataclasses with auto typecasting and other power features
Home-page: http://pypi.org/simple/powerdataclass
Author: Arish Pyne
Author-email: arishpyne@gmail.com
License: MIT
Classifier: Development Status :: 5 - Production/Stable
Classifier: Intended Audience :: Developers
Classifier: License :: OSI Approved :: MIT License
Classifier: Programming Language :: Python :: 3.11
Classifier: Topic :: Software Development :: Libraries :: Python Modules
Classifier: Typing :: Typed
Requires-Python: >=3.11
License-File: LICENSE
Requires-Dist: setuptools
Requires-Dist: toposort
